[{"t":"Speech at the ceremony awarding the Order of Parental Glory","d":"2009-01-13","u":"http://en.kremlin.ru/events/president/transcripts/speeches/2840","s":"Events\nSpeech at the ceremony awarding the Order of Parental","cat":"Politics & Government"},{"t":"Speech at the Ceremony Presenting National Awards to Representatives of Russian Media","d":"2009-01-16","u":"http://en.kremlin.ru/events/president/transcripts/speeches/2868","s":"Events\nSpeech at the Ceremony Presenting National Awards to ","cat":"Politics & Government"},{"t":"Speech at the Ceremony for the Presentation of Foreign Ambassadors' Letters of Credentials","d":"2009-01-16","u":"http://en.kremlin.ru/events/president/transcripts/speeches/2871","s":"Events\nSpeech at the Ceremony for the Presentation of Foreig","cat":"Economy & Business"},{"t":"Speech at the Performance Commemorating the 65th Anniversary of the Liberation of Leningrad from the Nazi Blockade","d":"2009-01-27","u":"http://en.kremlin.ru/events/president/transcripts/speeches/2966","s":"Events\nSpeech at the Performance Commemorating the 65th Anni","cat":"Politics & Government"},{"t":"Speech at the Enthronement Ceremony for Kirill, the Patriarch of Moscow and All Russia","d":"2009-02-01","u":"http://en.kremlin.ru/events/president/transcripts/speeches/3021","s":"Events\nSpeech at the Enthronement Ceremony for Kirill, the P","cat":"Society & Culture"},{"t":"Speech at a Reception Given by the President of Russia in Honour of Senior Clergy who Took Part in the Russian Orthodox ","d":"2009-02-02","u":"http://en.kremlin.ru/events/president/transcripts/speeches/3033","s":"Events\nSpeech at a Reception Given by the President of Russi","cat":"Society & Culture"},{"t":"Speech at Ceremony Awarding the 2008 Russian Federation President’s Prize for Science and Innovation by Young Scientists","d":"2009-02-09","u":"http://en.kremlin.ru/events/president/transcripts/speeches/3095","s":"Events\nSpeech at Ceremony Awarding the 2008 Russian Federati","cat":"Science & Health"},{"t":"Speech at the Opening of a Liquefied Natural Gas Production Plant","d":"2009-02-18","u":"http://en.kremlin.ru/events/president/transcripts/speeches/3224","s":"Events\nSpeech at the Opening of a Liquefied Natural Gas Prod","cat":"Economy & Business"},{"t":"Speech at the Gala Evening Celebrating Defenders of the Motherland Day","d":"2009-02-21","u":"http://en.kremlin.ru/events/president/transcripts/speeches/3270","s":"Events\nSpeech at the Gala Evening Celebrating Defenders of t","cat":"Military & Security"},{"t":"Speech at Ceremony Handing Back to Russia the Russian Orthodox Church Metochion in Bari","d":"2009-03-01","u":"http://en.kremlin.ru/events/president/transcripts/speeches/3323","s":"Events\nSpeech at Ceremony Handing Back to Russia the Russian","cat":"Society & Culture"},{"t":"Speech at Madrid’s Town Hall at the Ceremony of Presenting Mr Medvedev with the Symbolic Golden Key to the City","d":"2009-03-02","u":"http://en.kremlin.ru/events/president/transcripts/speeches/3335","s":"Events\nSpeech at Madrid’s Town Hall at the Ceremony of Prese","cat":"Politics & Government"},{"t":"Speech at the State Awards Presentation Ceremony","d":"2009-03-05","u":"http://en.kremlin.ru/events/president/transcripts/speeches/3362","s":"Events\nSpeech at the State Awards Presentation Ceremony\nMarc","cat":"Society & Culture"},{"t":"Speech at State Decorations Awarding Ceremony","d":"2009-04-10","u":"http://en.kremlin.ru/events/president/transcripts/speeches/3723","s":"Events\nSpeech at State Decorations Awarding Ceremony\nApril 1","cat":"Science & Health"},{"t":"Speech at State Decorations Awarding Ceremony","d":"2009-04-29","u":"http://en.kremlin.ru/events/president/transcripts/speeches/3907","s":"Events\nSpeech at State Decorations Awarding Ceremony\nApril 2","cat":"Science & Health"},{"t":"Speech at Concert Celebrating the 64th Anniversary of Victory in the Great Patriotic War","d":"2009-05-08","u":"http://en.kremlin.ru/events/president/transcripts/speeches/4010","s":"Events\nSpeech at Concert Celebrating the 64th Anniversary of","cat":"International Affairs"},{"t":"Speech at Military Parade in Honour of 64th Anniversary of Victory in Great Patriotic War","d":"2009-05-09","u":"http://en.kremlin.ru/events/president/transcripts/speeches/4015","s":"Events\nSpeech at Military Parade in Honour of 64th Anniversa","cat":"International Affairs"},{"t":"Speech at Reception in Honour of 64th Anniversary of Victory in Great Patriotic War","d":"2009-05-09","u":"http://en.kremlin.ru/events/president/transcripts/speeches/4016","s":"Events\nSpeech at Reception in Honour of 64th Anniversary of ","cat":"Military & Security"},{"t":"Speech at State Decorations Award Ceremony","d":"2009-05-20","u":"http://en.kremlin.ru/events/president/transcripts/speeches/4137","s":"Events\nSpeech at State Decorations Award Ceremony\nMay 20, 20","cat":"Society & Culture"},{"t":"Speech at Opening Ceremony of the Boris Yeltsin Presidential Library","d":"2009-05-27","u":"http://en.kremlin.ru/events/president/transcripts/speeches/4220","s":"Events\nSpeech at Opening Ceremony of the Boris Yeltsin Presi","cat":"Society & Culture"},{"t":"Speech at Presentation by Foreign Ambassadors of their Letters of Credence","d":"2009-05-29","u":"http://en.kremlin.ru/events/president/transcripts/speeches/4236","s":"Events\nSpeech at Presentation by Foreign Ambassadors of thei","cat":"International Affairs"},{"t":"Speech at Ceremony Awarding the Order of Parental Glory to Parents of Large Families","d":"2009-06-01","u":"http://en.kremlin.ru/events/president/transcripts/speeches/4252","s":"Events\nSpeech at Ceremony Awarding the Order of Parental Glo","cat":"Politics & Government"},{"t":"Speech at 2009 Global Energy International Prize Award Ceremony","d":"2009-06-05","u":"http://en.kremlin.ru/events/president/transcripts/speeches/4346","s":"Events\nSpeech at 2009 Global Energy International Prize Awar","cat":"Economy & Business"},{"t":"Opening Address at World Grain Forum","d":"2009-06-06","u":"http://en.kremlin.ru/events/president/transcripts/speeches/4358","s":"Events\nOpening Address at World Grain Forum\nJune 6, 2009\n21:","cat":"Economy & Business"},{"t":"Speech at Ceremony for Presenting the 2008 Russian National Awards","d":"2009-06-12","u":"http://en.kremlin.ru/events/president/transcripts/speeches/4425","s":"Events\nSpeech at Ceremony for Presenting the 2008 Russian Na","cat":"Science & Health"},{"t":"Speech at Reception Celebrating Day of Russia","d":"2009-06-12","u":"http://en.kremlin.ru/events/president/transcripts/speeches/4427","s":"Events\nSpeech at Reception Celebrating Day of Russia\nJune 12","cat":"Politics & Government"},{"t":"Speech at Gala Evening in Honour of 60th Anniversary of the Establishment of Diplomatic Relations between Russia and Chi","d":"2009-06-17","u":"http://en.kremlin.ru/events/president/transcripts/speeches/4498","s":"Events\nSpeech at Gala Evening in Honour of 60th Anniversary ","cat":"Politics & Government"},{"t":"Speech at Meeting with Military Academy Graduates","d":"2009-07-01","u":"http://en.kremlin.ru/events/president/transcripts/speeches/4680","s":"Events\nSpeech at Meeting with Military Academy Graduates\nJul","cat":"Military & Security"},{"t":"Address to Schoolchildren","d":"2009-09-01","u":"http://en.kremlin.ru/events/president/transcripts/speeches/48448","s":"Events\nAddress to Schoolchildren\nSeptember 1, 2009\n09:00\nDmi","cat":"Society & Culture"},{"t":"Speech at Moscow City Day Celebrations","d":"2009-09-05","u":"http://en.kremlin.ru/events/president/transcripts/speeches/48453","s":"Events\nSpeech at Moscow City Day Celebrations\nSeptember 5, 2","cat":"Economy & Business"},{"t":"Speech at State Decorations Presentation Ceremony","d":"2009-11-02","u":"http://en.kremlin.ru/events/president/transcripts/speeches/48493","s":"Events\nSpeech at State Decorations Presentation Ceremony\nNov","cat":"Science & Health"},{"t":"Ceremony Awarding State Decorations to Foreign Citizens Who Have Made a Great Contribution to Building Friendship and Co","d":"2009-11-04","u":"http://en.kremlin.ru/events/president/transcripts/speeches/48495","s":"Events\nCeremony Awarding State Decorations to Foreign Citize","cat":"Society & Culture"},{"t":"Speech at the Ceremony Unveiling a Memorial Chapel Honouring Prince Dmitry Pozharsky","d":"2009-11-04","u":"http://en.kremlin.ru/events/president/transcripts/speeches/48497","s":"Events\nSpeech at the Ceremony Unveiling a Memorial Chapel Ho","cat":"Society & Culture"},{"t":"Speech at Celebrations Marking the 20th Anniversary of the Berlin Wall’s Fall","d":"2009-11-09","u":"http://en.kremlin.ru/events/president/transcripts/speeches/48500","s":"Events\nSpeech at Celebrations Marking the 20th Anniversary o","cat":"Military & Security"},{"t":"Award Ceremony for Outstanding Gun Designer Mikhail Kalashnikov","d":"2009-11-10","u":"http://en.kremlin.ru/events/president/transcripts/speeches/48501","s":"Events\nAward Ceremony for Outstanding Gun Designer Mikhail K","cat":"Military & Security"},{"t":"Speech at Police Day Celebratory Event","d":"2009-11-10","u":"http://en.kremlin.ru/events/president/transcripts/speeches/48504","s":"Events\nSpeech at Police Day Celebratory Event\nNovember 10, 2","cat":"Politics & Government"},{"t":"Speech at Ceremony Awarding Decorations to Veterans of the Great Patriotic War","d":"2009-12-04","u":"http://en.kremlin.ru/events/president/transcripts/speeches/48526","s":"Events\nSpeech at Ceremony Awarding Decorations to Veterans o","cat":"Military & Security"},{"t":"Speech at Official Reception Celebrating International Paralympic Day","d":"2009-12-12","u":"http://en.kremlin.ru/events/president/transcripts/speeches/48533","s":"Events\nSpeech at Official Reception Celebrating Internationa","cat":"Politics & Government"},{"t":"Speech at Ceremonial Presentation of Ensign of Foreign Intelligence Service and Personal Standard of the Service’s Direc","d":"2009-12-15","u":"http://en.kremlin.ru/events/president/transcripts/speeches/48535","s":"Events\nSpeech at Ceremonial Presentation of Ensign of Foreig","cat":"Politics & Government"},{"t":"Speech at Gala Night Celebrating National Security Services Day","d":"2009-12-17","u":"http://en.kremlin.ru/events/president/transcripts/speeches/48538","s":"Events\nSpeech at Gala Night Celebrating National Security Se","cat":"Politics & Government"},{"t":"Speech at National Youth Winners’ Forum Proryv","d":"2009-12-17","u":"http://en.kremlin.ru/events/president/transcripts/speeches/48539","s":"Events\nSpeech at National Youth Winners’ Forum Proryv\nDecemb","cat":"Economy & Business"},{"t":"Speech at State Decorations Awarding Ceremony","d":"2009-12-28","u":"http://en.kremlin.ru/events/president/transcripts/speeches/48546","s":"Events\nSpeech at State Decorations Awarding Ceremony\nDecembe","cat":"Society & Culture"},{"t":"Speech at Sangtuda-1 Hydroelectric Power Station Inauguration Ceremony","d":"2009-07-31","u":"http://en.kremlin.ru/events/president/transcripts/speeches/4985","s":"Events\nSpeech at Sangtuda-1 Hydroelectric Power Station Inau","cat":"Economy & Business"},{"t":"Speech at Reception in Honour of Russian Servicemen","d":"2009-08-08","u":"http://en.kremlin.ru/events/president/transcripts/speeches/5147","s":"Events\nSpeech at Reception in Honour of Russian Servicemen\nA","cat":"Military & Security"},{"t":"Opening Remarks at Ceremony Presenting Russian State Awards to Employees at Russian-Mongolian Company Mongolrostsvetmet","d":"2009-08-26","u":"http://en.kremlin.ru/events/president/transcripts/speeches/5281","s":"Events\nOpening Remarks at Ceremony Presenting Russian State ","cat":"Politics & Government"},{"t":"Opening Remarks at Meeting of the Commission for Modernisation and Technological Development of Russia’s Economy","d":"2009-08-31","u":"http://en.kremlin.ru/events/president/transcripts/speeches/5333","s":"Events\nOpening Remarks at Meeting of the Commission for Mode","cat":"Economy & Business"},{"t":"Speech at State Decorations Ceremony for Olympic Champions and Medal Winners at 2008 Beijing Olympic Games","d":"2009-09-08","u":"http://en.kremlin.ru/events/president/transcripts/speeches/5395","s":"Events\nSpeech at State Decorations Ceremony for Olympic Cham","cat":"Sports"},{"t":"Speech at Ceremony Marking 210th Anniversary of Alexander Suvorov's Alpine Campaign","d":"2009-09-22","u":"http://en.kremlin.ru/events/president/transcripts/speeches/5540","s":"Events\nSpeech at Ceremony Marking 210th Anniversary of Alexa","cat":"Military & Security"},{"t":"Speech at Ceremony Presenting State Decorations to Servicemen who Participated in the Caucasus-2009 Strategic Exercises","d":"2009-09-28","u":"http://en.kremlin.ru/events/president/transcripts/speeches/5601","s":"Events\nSpeech at Ceremony Presenting State Decorations to Se","cat":"Military & Security"},{"t":"Speech at Award Ceremony for Winners of 2009 Russian Teacher of the Year Competition","d":"2009-10-05","u":"http://en.kremlin.ru/events/president/transcripts/speeches/5663","s":"Events\nSpeech at Award Ceremony for Winners of 2009 Russian ","cat":"Society & Culture"},{"t":"Speech at National Sports Forum: Russia – Country of Sports","d":"2009-10-23","u":"http://en.kremlin.ru/events/president/transcripts/speeches/5805","s":"Events\nSpeech at National Sports Forum: Russia – Country of ","cat":"Sports"},{"t":"New Year’s Address to the Nation","d":"2009-12-31","u":"http://en.kremlin.ru/events/president/transcripts/speeches/6557","s":"Events\nNew Year’s Address to the Nation\nDecember 31, 2009\n23","cat":"Politics & Government"}]